CHANGELOG.md
setprogramoptions/SetProgramOptions.py
setprogramoptions/SetProgramOptionsCMake.py
setprogramoptions/__init__.py
setprogramoptions/common.py
setprogramoptions/unittests/__init__.py
setprogramoptions/unittests/common.py
setprogramoptions/unittests/files_ini/config_test_setprogramoptions.ini
setprogramoptions/unittests/test_SetProgramOptions.py
setprogramoptions/unittests/test_SetProgramOptionsCMake.py
setprogramoptions/version.py
setprogramoptions-0.5.0.3.dist-info/LICENSE
setprogramoptions-0.5.0.3.dist-info/METADATA
setprogramoptions-0.5.0.3.dist-info/WHEEL
setprogramoptions-0.5.0.3.dist-info/RECORD
