Metadata-Version: 2.1
Name: setprogramoptions
Version: 0.5.0.3
Summary: Program options configuration file reader using ConfigParserEnhanced.
Home-page: https://github.com/sandialabs/SetProgramOptions
License: LICENSE
Keywords: Utility,Bash,Configuration,ConfigParserEnhanced,ConfigParser
Author: William McLendon
Author-email: wcmclen@sandia.gov
Requires-Python: >=3.6,<4.0
Classifier: Development Status :: 5 - Production/Stable
Classifier: Intended Audience :: Developers
Classifier: Intended Audience :: Other Audience
Classifier: Intended Audience :: System Administrators
Classifier: License :: OSI Approved :: BSD License
Classifier: License :: Other/Proprietary License
Classifier: Programming Language :: Python :: 3
Classifier: Programming Language :: Python :: 3.6
Classifier: Programming Language :: Python :: 3.7
Classifier: Programming Language :: Python :: 3.8
Classifier: Programming Language :: Python :: 3.9
Classifier: Programming Language :: Python :: 3.10
Classifier: Programming Language :: Python :: 3.11
Classifier: Programming Language :: Python :: 3 :: Only
Requires-Dist: configparser (>=5.0,<6.0)
Requires-Dist: configparserenhanced (>=0.8,<0.9)
Project-URL: CI, https://github.com/sandialabs/SetProgramOptions/actions
Project-URL: Documentation, https://setprogramoptions.readthedocs.io/en/latest/
Project-URL: Issues, https://github.com/sandialabs/SetProgramOptions/issues
Project-URL: Repository, https://github.com/sandialabs/SetProgramOptions
